kalimera/__init__.py
kalimera/source.py
kalimera-4.0.0.dist-info/LICENSE
kalimera-4.0.0.dist-info/METADATA
kalimera-4.0.0.dist-info/WHEEL
kalimera-4.0.0.dist-info/top_level.txt
kalimera-4.0.0.dist-info/RECORD
