Metadata-Version: 2.1
Name: kalimera
Version: 4.0.0
Summary: Hello world
Author: Chris (Christoforos Eseroglou)
Author-email: chriseseroglou@gmail.com
Keywords: python
Classifier: Development Status :: 1 - Planning
Classifier: Intended Audience :: Developers
Classifier: Programming Language :: Python :: 3
Classifier: License :: OSI Approved :: MIT License
Classifier: Operating System :: Unix
Classifier: Operating System :: MacOS :: MacOS X
Classifier: Operating System :: Microsoft :: Windows
License-File: LICENSE
